README.md
setup.py
smart_error_handler/__init__.py
smart_error_handler/handler.py
smart_error_handler/logger.py
smart_error_handler/smart_error_handler.py
smart_error_handler/suggestions.py
smart_error_handler.egg-info/PKG-INFO
smart_error_handler.egg-info/SOURCES.txt
smart_error_handler.egg-info/dependency_links.txt
smart_error_handler.egg-info/top_level.txt