Metadata-Version: 2.1
Name: smart-error-handler
Version: 0.3
Summary: A smart error handler
Home-page: https://github.com/Momwhyareyouhere/Smart-error-handler
Author: Momwhyareyouhere
Author-email: momwhyareyouhere51@gmail.com
